LICENSE
MANIFEST.in
readme.md
setup.cfg
setup.py
smartcloudadmin/__init__.py
smartcloudadmin/config.py
smartcloudadmin/enums.py
smartcloudadmin/exceptions.py
smartcloudadmin/http_requests.py
smartcloudadmin.egg-info/PKG-INFO
smartcloudadmin.egg-info/SOURCES.txt
smartcloudadmin.egg-info/dependency_links.txt
smartcloudadmin.egg-info/requires.txt
smartcloudadmin.egg-info/top_level.txt
smartcloudadmin/json/__init__.py
smartcloudadmin/json/change_password.json
smartcloudadmin/json/register_customer.json
smartcloudadmin/json/register_subscriber.json
smartcloudadmin/json/register_subscription.json
smartcloudadmin/json/set_one_time_password.json
smartcloudadmin/json/set_user_password.json
smartcloudadmin/models/__init__.py
smartcloudadmin/models/address_set.py
smartcloudadmin/models/contact.py
smartcloudadmin/models/organization.py
smartcloudadmin/models/seat.py
smartcloudadmin/models/subscriber.py
smartcloudadmin/models/subscription.py
smartcloudadmin/utils/__init__.py
smartcloudadmin/utils/decorators.py
smartcloudadmin/utils/generators.py
smartcloudadmin/utils/generic.py
smartcloudadmin/utils/json_constructor.py
smartcloudadmin/utils/qol.py